docker_hosts/__init__.py
docker_hosts/cli.py
docker_hosts-0.1.1.dist-info/WHEEL
docker_hosts-0.1.1.dist-info/entry_points.txt
docker_hosts-0.1.1.dist-info/METADATA
docker_hosts-0.1.1.dist-info/RECORD
