Metadata-Version: 2.3
Name: docker-hosts
Version: 0.1.1
Summary: Automatically manage Docker container hostnames in /etc/hosts for local development and CI
Keywords: docker,docker-compose,hosts,localhost,development,devops,containers,networking,automation
Author: Michael Bianco
Author-email: Michael Bianco <mike@mikebian.co>
Requires-Dist: click
Requires-Dist: docker
Requires-Dist: structlog-config
Requires-Python: >=3.11
Project-URL: Repository, https://github.com/iloveitaly/docker-hosts
